COPYING
MANIFEST.in
README.rst
setup.py
django_sasco/__init__.py
django_sasco/exceptions.py
django_sasco.egg-info/PKG-INFO
django_sasco.egg-info/SOURCES.txt
django_sasco.egg-info/dependency_links.txt
django_sasco.egg-info/top_level.txt
django_sasco/forms/__init__.py
django_sasco/forms/dictionary_selector.py
django_sasco/models/AbstractModel.py
django_sasco/models/AbstractUser.py
django_sasco/models/__init__.py
django_sasco/static/webpush/webpush.js
django_sasco/templates/400.html
django_sasco/templates/403.html
django_sasco/templates/404.html
django_sasco/templates/500.html
django_sasco/templates/webpush_button.html
django_sasco/templatetags/__init__.py
django_sasco/templatetags/alert_helper.py
django_sasco/templatetags/date_string_to_date.py
django_sasco/templatetags/form_helper.py
django_sasco/templatetags/mathematical_operations.py
django_sasco/utils/__init__.py
django_sasco/utils/base64.py
django_sasco/utils/dictionary_merge.py
django_sasco/utils/dictionary_selector.py
django_sasco/utils/email.py
django_sasco/utils/is_empty.py
django_sasco/utils/is_set.py
django_sasco/utils/log.py