Metadata-Version: 1.1
Name: django-sasco
Version: 1.0.1
Summary: Python module with an application base for django framework, used in SASCO company.
Home-page: https://github.com/sascocl/django-sasco
Author: SASCO SpA
Author-email: hola@sasco.cl
License: LGPL
Keywords: django
Platform: UNKNOWN
Classifier: Development Status :: 5 - Production/Stable
Classifier: Intended Audience :: Developers
Classifier: Topic :: Software Development :: Build Tools
Classifier: License :: OSI Approved :: GNU Lesser General Public License v3 or later (LGPLv3+)
Classifier: Programming Language :: Python :: 3
Classifier: Framework :: Django
